[
    {"name": "Goodgood Restaurant", "rate": 3, "city": "Sydney", "open": "10am", "close": "6pm", "food": ["lunch", "dessert"]},
    {"name": "Happy Eats", "rate": 4, "city": "Melbourne", "open": "9am", "close": "5pm", "food": ["breakfast", "lunch"]},
    {"name": "Sunset Diner", "rate": 5, "city": "Brisbane", "open": "11am", "close": "10pm", "food": ["dinner", "dessert"]},
    {"name": "Morning Joe's", "rate": 3, "city": "Perth", "open": "5am", "close": "12pm", "food": ["breakfast", "coffee"]},
    {"name": "Garden Bistro", "rate": 4, "city": "Adelaide", "open": "8am", "close": "8pm", "food": ["lunch", "dinner"]},
    {"name": "Riverside Cafe", "rate": 2, "city": "Hobart", "open": "7am", "close": "4pm", "food": ["coffee", "snacks"]},
    {"name": "Ocean View", "rate": 5, "city": "Darwin", "open": "1pm", "close": "11pm", "food": ["dinner", "drinks"]},
    {"name": "Urban Plates", "rate": 4, "city": "Canberra", "open": "10am", "close": "9pm", "food": ["lunch", "dinner"]},
    {"name": "Spice Journey", "rate": 5, "city": "Sydney", "open": "12pm", "close": "10pm", "food": ["lunch", "dinner"]},
    {"name": "Leaf & Bean", "rate": 3, "city": "Melbourne", "open": "6am", "close": "6pm", "food": ["breakfast", "coffee"]},
    {"name": "Night Owl", "rate": 4, "city": "Brisbane", "open": "6pm", "close": "4am", "food": ["dinner", "late night"]},
    {"name": "Seaside Snacks", "rate": 2, "city": "Perth", "open": "10am", "close": "5pm", "food": ["lunch", "snacks"]},
    {"name": "Mountain Grill", "rate": 5, "city": "Adelaide", "open": "7am", "close": "10pm", "food": ["breakfast", "dinner"]},
    {"name": "Urban Eatery", "rate": 3, "city": "Hobart", "open": "8am", "close": "8pm", "food": ["lunch", "dinner"]},
    {"name": "Harbor House", "rate": 4, "city": "Darwin", "open": "11am", "close": "11pm", "food": ["lunch", "dinner"]},
    {"name": "City Bites", "rate": 3, "city": "Canberra", "open": "9am", "close": "6pm", "food": ["breakfast", "lunch"]},
    {"name": "Grand Feast", "rate": 4, "city": "Sydney", "open": "12pm", "close": "9pm", "food": ["lunch", "dinner"]},
    {"name": "Corner Café", "rate": 2, "city": "Melbourne", "open": "8am", "close": "4pm", "food": ["breakfast", "lunch"]},
    {"name": "Pier Dining", "rate": 5, "city": "Brisbane", "open": "1pm", "close": "11pm", "food": ["lunch", "dinner"]},
    {"name": "Street Eats", "rate": 4, "city": "Perth", "open": "11am", "close": "8pm", "food": ["lunch", "snacks"]},
    {"name": "Night Owl1", "rate": 4, "city": "Brisbane", "open": "7pm", "close": "4am", "food": ["dinner", "late night"]},
    {"name": "Seaside Snacks1", "rate": 2, "city": "Perth", "open": "5am", "close": "5pm", "food": ["lunch", "snacks"]},
    {"name": "Mountain Grill1", "rate": 5, "city": "Adelaide", "open": "7am", "close": "10pm", "food": ["breakfast", "dinner"]},
    {"name": "Urban Eatery1", "rate": 3, "city": "Hobart", "open": "6am", "close": "8pm", "food": ["lunch", "dinner"]},
    {"name": "Harbor House1", "rate": 4, "city": "Darwin", "open": "11am", "close": "11pm", "food": ["lunch", "dinner"]},
    {"name": "City Bites1", "rate": 3, "city": "Canberra", "open": "9am", "close": "6pm", "food": ["breakfast", "lunch"]},
    {"name": "Grand Feast1", "rate": 4, "city": "Sydney", "open": "10pm", "close": "9pm", "food": ["lunch", "dinner"]},
    {"name": "Corner Café1", "rate": 2, "city": "Melbourne", "open": "8am", "close": "4pm", "food": ["breakfast", "lunch"]},
    {"name": "Pier Dining1", "rate": 5, "city": "Brisbane", "open": "1pm", "close": "11pm", "food": ["lunch", "dinner"]},
    {"name": "Street Eats1", "rate": 4, "city": "Perth", "open": "1am", "close": "8pm", "food": ["lunch", "snacks"]},
    {"name": "Blue Sky Diner", "rate": 4, "city": "Sydney", "open": "7am", "close": "9pm", "food": ["breakfast", "dinner"]},
    {"name": "The Green Room", "rate": 3, "city": "Melbourne", "open": "9am", "close": "10pm", "food": ["lunch", "dessert"]},
    {"name": "Harbor Lights", "rate": 5, "city": "Perth", "open": "12pm", "close": "12am", "food": ["dinner", "drinks"]},
    {"name": "Sunset Café", "rate": 2, "city": "Brisbane", "open": "6am", "close": "6pm", "food": ["coffee", "snacks"]},
    {"name": "Urban Grill", "rate": 4, "city": "Adelaide", "open": "11am", "close": "10pm", "food": ["lunch", "dinner"]},
    {"name": "Riverbank Eatery", "rate": 5, "city": "Canberra", "open": "8am", "close": "8pm", "food": ["breakfast", "lunch"]},
    {"name": "City Lights Bistro", "rate": 3, "city": "Darwin", "open": "10am", "close": "11pm", "food": ["lunch", "dinner"]},
    {"name": "Garden Deli", "rate": 4, "city": "Hobart", "open": "7am", "close": "5pm", "food": ["breakfast", "lunch"]}
]
